dvlogger/__init__.py
dvlogger/logconfig.py
dvlogger-0.2.1.dist-info/METADATA
dvlogger-0.2.1.dist-info/WHEEL
dvlogger-0.2.1.dist-info/top_level.txt
dvlogger-0.2.1.dist-info/RECORD
